{"stats":{"minecraft:picked_up":{"minecraft:potato":1},"minecraft:mined":{"minecraft:spruce_leaves":1},"minecraft:custom":{"minecraft:jump":209,"minecraft:time_since_rest":20392,"minecraft:leave_game":1,"minecraft:crouch_one_cm":675,"minecraft:play_one_minute":20392,"minecraft:damage_taken":219,"minecraft:sprint_one_cm":27325,"minecraft:walk_on_water_one_cm":2502,"minecraft:time_since_death":20392,"minecraft:walk_one_cm":16675,"minecraft:sneak_time":156,"minecraft:walk_under_water_one_cm":319,"minecraft:swim_one_cm":3926,"minecraft:fly_one_cm":33465},"minecraft:used":{"minecraft:bread":6}},"DataVersion":2230}