{"stats":{"minecraft:crafted":{"minecraft:oak_planks":40,"minecraft:crafting_table":1,"minecraft:chest":1,"minecraft:furnace":1,"minecraft:acacia_planks":72,"minecraft:acacia_stairs":4},"minecraft:picked_up":{"minecraft:stick":4,"minecraft:leather":1,"minecraft:porkchop":1,"minecraft:acacia_log":13,"minecraft:golden_shovel":1,"minecraft:sand":6,"minecraft:oak_log":10,"minecraft:acacia_stairs":1,"minecraft:spider_eye":1,"minecraft:dirt":2,"minecraft:acacia_planks":27,"minecraft:wheat_seeds":1,"minecraft:beef":1,"minecraft:iron_ore":2,"minecraft:oak_planks":4,"minecraft:cobblestone":10,"minecraft:sunflower":2},"minecraft:killed":{"minecraft:pig":2,"minecraft:zombie":1,"minecraft:spider":1,"minecraft:cow":4},"minecraft:mined":{"minecraft:acacia_leaves":3,"minecraft:iron_ore":2,"minecraft:sweet_berry_bush":1,"minecraft:acacia_stairs":1,"minecraft:grass":11,"minecraft:acacia_log":33,"minecraft:oak_log":10,"minecraft:dead_bush":1,"minecraft:sand":13,"minecraft:dirt":2,"minecraft:acacia_planks":33,"minecraft:stone":14,"minecraft:oak_planks":4,"minecraft:sandstone":10,"minecraft:oak_leaves":3},"minecraft:custom":{"minecraft:time_since_rest":46223,"minecraft:interact_with_furnace":1,"minecraft:sprint_one_cm":77746,"minecraft:damage_taken":195,"minecraft:walk_one_cm":134791,"minecraft:mob_kills":8,"minecraft:drop":1,"minecraft:damage_dealt":185,"minecraft:interact_with_crafting_table":7,"minecraft:fly_one_cm":101098,"minecraft:open_chest":3,"minecraft:play_one_minute":46223,"minecraft:crouch_one_cm":3353,"minecraft:sneak_time":2072,"minecraft:walk_under_water_one_cm":5124,"minecraft:jump":668,"minecraft:leave_game":1,"minecraft:walk_on_water_one_cm":30900,"minecraft:time_since_death":46223},"minecraft:used":{"minecraft:acacia_stairs":4,"minecraft:stone_sword":88,"minecraft:acacia_log":15,"minecraft:stone_shovel":13,"minecraft:bread":1,"minecraft:stone_pickaxe":26,"minecraft:oak_planks":37,"minecraft:chest":1,"minecraft:stone_axe":89,"minecraft:dirt":1,"minecraft:crafting_table":1,"minecraft:porkchop":5,"minecraft:furnace":1,"minecraft:oak_sapling":2,"minecraft:acacia_planks":84},"minecraft:dropped":{"minecraft:porkchop":1}},"DataVersion":2230}